xontrib/term_integration.py
xontrib_term_integrations/__init__.py
xontrib_term_integrations/iterm2.py
xontrib_term_integrations/kitty.py
xontrib_term_integrations/kitty_completions.py
xontrib_term_integrations/utils.py
xontrib_term_integrations/wezterm.py
xontrib_term_integrations-0.2.0.dist-info/WHEEL
xontrib_term_integrations-0.2.0.dist-info/METADATA
xontrib_term_integrations-0.2.0.dist-info/licenses/LICENSE
xontrib_term_integrations-0.2.0.dist-info/RECORD
