Metadata-Version: 2.1
Name: xontrib-term-integrations
Version: 0.2.0
Summary: Support shell integration of terminal programs iTerm2, Kitty...
License: MIT
Keywords: xontrib,xonsh
Author-email: Noortheen Raja NJ <jnoortheen@gmail.com>
Requires-Python: >=3.8
Classifier: Intended Audience :: Developers
Classifier: License :: OSI Approved :: MIT License
Classifier: Natural Language :: English
Classifier: Operating System :: OS Independent
Classifier: Programming Language :: Python
Classifier: Programming Language :: Python :: 3
Classifier: Topic :: System :: Shells
Classifier: Topic :: System :: System Shells
Classifier: Topic :: Terminals
Requires-Dist: xonsh>=0.12.0
Provides-Extra: dev
Requires-Dist: pytest; extra == "dev"
Requires-Dist: black; extra == "dev"
Project-URL: Code, https://github.com/jnoortheen/xontrib-term-integrations
Project-URL: Documentation, https://github.com/jnoortheen/xontrib-term-integrations/blob/master/README.md
Project-URL: Issue tracker, https://github.com/jnoortheen/xontrib-term-integrations/issues
Project-URL: repository, https://github.com/jnoortheen/xontrib-term-integrations
